MANIFEST.in
README.rst
extconvert.py
setup.py
dnsextlang/__init__.py
dnsextlang/exceptions.py
dnsextlang/extfield.py
dnsextlang/extlang.py
dnsextlang/extrec.py
dnsextlang/rrtypes.txt
dnsextlang.egg-info/PKG-INFO
dnsextlang.egg-info/SOURCES.txt
dnsextlang.egg-info/dependency_links.txt
dnsextlang.egg-info/requires.txt
dnsextlang.egg-info/top_level.txt
test/__init__.py
test/extlangtests.py