Metadata-Version: 1.1
Name: dnsextlang
Version: 1.3
Summary: DNS extension language parser and web form helper
Home-page: https://www.taugh.com/dnsextlang/
Author: John Levine
Author-email: johnl@taugh.com
License: BSD
Keywords: dns rrtypes extensions
Platform: UNKNOWN
Classifier: Development Status :: 3 - Alpha
Classifier: Intended Audience :: Developers
Classifier: Programming Language :: Python :: 3
Classifier: Programming Language :: Python :: 3.3
Classifier: Programming Language :: Python :: 3.4
Classifier: Programming Language :: Python :: 3.5
Classifier: Programming Language :: Python :: 3.6
